[{"key":"Aceh","value":"Aceh"},{"key":"Sumatera Utara","value":"Sumatera Utara"},{"key":"Sumatera Barat","value":"Sumatera Barat"},{"key":"Riau","value":"Riau"},{"key":"Jambi","value":"Jambi"},{"key":"Sumatera Selatan","value":"Sumatera Selatan"},{"key":"Bengkulu","value":"Bengkulu"},{"key":"Lampung","value":"Lampung"},{"key":"Kepulauan Bangka Belitung","value":"Kepulauan Bangka Belitung"},{"key":"Kepulauan Riau","value":"Kepulauan Riau"},{"key":"DKI Jakarta","value":"DKI Jakarta"},{"key":"Jawa Barat","value":"Jawa Barat"},{"key":"Jawa Tengah","value":"Jawa Tengah"},{"key":"Daerah Istimewa Yogyakarta","value":"Daerah Istimewa Yogyakarta"},{"key":"Jawa Timur","value":"Jawa Timur"},{"key":"Banten","value":"Banten"},{"key":"Bali","value":"Bali"},{"key":"Nusa Tenggara Barat","value":"Nusa Tenggara Barat"},{"key":"Nusa Tenggara Timur","value":"Nusa Tenggara Timur"},{"key":"Kalimantan Barat","value":"Kalimantan Barat"},{"key":"Kalimantan Tengah","value":"Kalimantan Tengah"},{"key":"Kalimantan Selatan","value":"Kalimantan Selatan"},{"key":"Kalimantan Timur","value":"Kalimantan Timur"},{"key":"Kalimantan Utara","value":"Kalimantan Utara"},{"key":"Sulawesi Utara","value":"Sulawesi Utara"},{"key":"Sulawesi Tengah","value":"Sulawesi Tengah"},{"key":"Sulawesi Selatan","value":"Sulawesi Selatan"},{"key":"Sulawesi Tenggara","value":"Sulawesi Tenggara"},{"key":"Gorontalo","value":"Gorontalo"},{"key":"Sulawesi Barat","value":"Sulawesi Barat"},{"key":"Maluku","value":"Maluku"},{"key":"Maluku Utara","value":"Maluku Utara"},{"key":"Papua","value":"Papua"},{"key":"Papua Barat Daya","value":"Papua Barat Daya"},{"key":"Papua Barat","value":"Papua Barat"},{"key":"Papua Selatan","value":"Papua Selatan"},{"key":"Papua Tengah","value":"Papua Tengah"},{"key":"Papua Pegunungan","value":"Papua Pegunungan"}]